{
  "winject_rrc_config" :{
    "frame80211_config" : {
      "slot_intvl_us" : 1000,
      "fec_config" : [
        {
          "fec_type" : "RS(255,239)",
          "threshold" : 10
        },
        {
          "fec_type" : "RS(255,223)",
          "threshold" : 20
        },
        {
          "fec_type" : "RS(255,191)",
          "threshold" : 40
        },
        {
          "fec_type" : "RS(255,127)",
          "threshold" : 80
        }
      ]
    },
    "llc_configs": [
      {
        "lcid" : 0,
        "tx_mode" : "transparent",
        "scheduling_config" : {
          "guaranteed_pdu_size" : -1,
          "scheduling_quanta" : 0
        },
        "tx_config" :
        {
          "crc" : "CRC32(04C11DB7)"
        }
      },
      {
        "lcid" : 1,
        "tx_mode" : "transparent",
        "scheduling_config" : {
          "guaranteed_pdu_size" : -1,
          "scheduling_quanta" : 0
        }
      },
      {
        "lcid" : 2,
        "tx_mode" : "transparent",
        "scheduling_config" : {
          "guaranteed_pdu_size" : 0,
          "scheduling_quanta" : 255
        }
      },
      {
        "lcid" : 3,
        "tx_mode" : "acknowledged",
        "scheduling_config" : {
          "guaranteed_pdu_size" : 5,
          "scheduling_quanta" : 64
        },
        "tx_config" : {
          "retx_slot_count" : 10,
          "max_retx_count" : 3,
          "crc" : "CRC32(04C11DB7)"
        }
      }
    ],
    "pdcp_configs": [
      {
        "description" : "RRC",
        "lcid" : 0,
        "type" : "internal",
        "allow_segmentation" : false
      },
      {
        "description" : "UART",
        "lcid" : 1,
        "type" : "uart",
        "device" : "/dev/ttyS0",
        "allow_segmentation" : false
      },
      {
        "description" : "video",
        "lcid" : 2,
        "type" : "udp",
        "portin" : 1010,
        "portout" : 1011,
        "allow_segmentation" : true
      },
      {
        "description" : "Tunnel",
        "lcid" : 3,
        "type" : "tun",
        "device" : "/dev/tun0",
        "allow_segmentation" : true
      }
    ]
  }
}